{
	"events": [
		{
			"animation": "[Default]",
			"animation_length": 0,
			"change_mirror_portrait": false,
			"change_z_index": false,
			"character": "character-1654055576.json",
			"event_id": "dialogic_002",
			"mirror_portrait": false,
			"portrait": "Default",
			"portrait_definition": "",
			"position": {
				"0": false,
				"1": false,
				"2": false,
				"3": false,
				"4": false
			},
			"type": 0,
			"z_index": 0
		},
		{
			"character": "character-1654055576.json",
			"event_id": "dialogic_001",
			"portrait": "",
			"text": "I'm the upgrade merchant! Would you like to purchase upgrades?"
		},
		{
			"character": "character-1654055576.json",
			"event_id": "dialogic_010",
			"options": [

			],
			"portrait": "",
			"question": "Take your time..."
		},
		{
			"choice": "Yes",
			"condition": "",
			"definition": "",
			"event_id": "dialogic_011",
			"value": ""
		},
		{
			"emit_signal": "open_upgrade_menu",
			"event_id": "dialogic_040"
		},
		{
			"choice": "No",
			"condition": "",
			"definition": "",
			"event_id": "dialogic_011",
			"value": ""
		},
		{
			"event_id": "dialogic_013"
		}
	],
	"metadata": {
		"dialogic-version": "1.4.2 - Dev",
		"file": "timeline-1654055612.json",
		"name": "upgrade_dialogue"
	}
}
